{
    "title": "Mathematical Modeling of Chemical Engineering Processes",
    "label": "f18-06623",
    "year": 2018,
    "semester": "Fall",
    "submit-email": "submiss.4glx1tp7z1ajg41f@u.box.com",
    "course-url": "https://github.com/jkitchin/f18-06623/",
    "course-raw-url": "https://raw.githubusercontent.com/jkitchin/f18-06623/master/",
    "instructor": "John Kitchin",
    "instructor-email": "jkitchin@andrew.cmu.edu",
    "admin-names": [
        "John Kitchin",
        "Mingjie Liu",
        "Noriyuki Yoshio"
    ],
    "admin-andrewids": [
        "jkitchin",
        "mingjie1",
        "nyoshio"
    ],
    "local-box-path": "~/Box Sync/f18-06623"
}